lakestream-0.0.3.dist-info/METADATA
lakestream-0.0.3.dist-info/WHEEL
lakestream/__init__.py
lakestream/__main__.py
lakestream/lakestream.cpython-311-darwin.so
lakestream-0.0.3.dist-info/RECORD
