Metadata-Version: 2.1
Name: lakestream
Version: 0.0.3
Classifier: Development Status :: 3 - Alpha
Classifier: Intended Audience :: Developers
Classifier: License :: OSI Approved :: MIT License
Classifier: Programming Language :: Python :: 3
Classifier: Programming Language :: Python :: 3.7
Classifier: Programming Language :: Python :: 3.8
Classifier: Programming Language :: Python :: 3.9
Classifier: Programming Language :: Python :: 3.10
Classifier: Programming Language :: Python :: 3.11
Summary: Python interface for Lakestream
Keywords: serverless,data,api
Maintainer-email: Anthony Potappel <aprxi@lakestream.dev>
License: MIT
Requires-Python: >=3.7
